yantu_python_util/__init__.py
yantu_python_util/operate_json.py
yantu_python_util-0.0.8.dist-info/LICENSE.txt
yantu_python_util-0.0.8.dist-info/METADATA
yantu_python_util-0.0.8.dist-info/WHEEL
yantu_python_util-0.0.8.dist-info/top_level.txt
yantu_python_util-0.0.8.dist-info/RECORD
