Metadata-Version: 2.1
Name: yantu-python-util
Version: 0.0.8
Summary: yantu python operate util
Home-page: https://github.com/HUSTAI/yantu-python-util
Author: sunhb
Author-email: 598924626@qq.com
Classifier: Programming Language :: Python :: 3
Classifier: License :: OSI Approved :: MIT License
Classifier: Operating System :: OS Independent
License-File: LICENSE.txt
